xingapi/__init__.py
xingapi/api/__init__.py
xingapi/api/log.py
xingapi/api/res.py
xingapi/api/xaquery.py
xingapi/api/xareal.py
xingapi/api/xasession.py
xingapi/api/resfiles/B7_.res
xingapi/api/resfiles/B7__1.res
xingapi/api/resfiles/BMT.res
xingapi/api/resfiles/BMT_1.res
xingapi/api/resfiles/BM_.res
xingapi/api/resfiles/BM__1.res
xingapi/api/resfiles/C01.res
xingapi/api/resfiles/C01_1.res
xingapi/api/resfiles/CCEAQ01100.res
xingapi/api/resfiles/CCEAQ01100_1.res
xingapi/api/resfiles/CCEAQ06000.res
xingapi/api/resfiles/CCEAQ06000_1.res
xingapi/api/resfiles/CCEAQ10100.res
xingapi/api/resfiles/CCEAQ10100_1.res
xingapi/api/resfiles/CCEAQ50600.res
xingapi/api/resfiles/CCEAQ50600_1.res
xingapi/api/resfiles/CCEAT00100.res
xingapi/api/resfiles/CCEAT00100_1.res
xingapi/api/resfiles/CCEAT00200.res
xingapi/api/resfiles/CCEAT00200_1.res
xingapi/api/resfiles/CCEAT00300.res
xingapi/api/resfiles/CCEAT00300_1.res
xingapi/api/resfiles/CCEBQ10500.res
xingapi/api/resfiles/CCEBQ10500_1.res
xingapi/api/resfiles/CD0.res
xingapi/api/resfiles/CD0_1.res
xingapi/api/resfiles/CDPCQ04700.res
xingapi/api/resfiles/CDPCQ04700_1.res
xingapi/api/resfiles/CEXAQ21100.res
xingapi/api/resfiles/CEXAQ21100_1.res
xingapi/api/resfiles/CEXAQ21200.res
xingapi/api/resfiles/CEXAQ21200_1.res
xingapi/api/resfiles/CEXAQ31100.res
xingapi/api/resfiles/CEXAQ31100_1.res
xingapi/api/resfiles/CEXAQ31200.res
xingapi/api/resfiles/CEXAQ31200_1.res
xingapi/api/resfiles/CEXAQ44200.res
xingapi/api/resfiles/CEXAQ44200_1.res
xingapi/api/resfiles/CEXAT11100.res
xingapi/api/resfiles/CEXAT11100_1.res
xingapi/api/resfiles/CEXAT11200.res
xingapi/api/resfiles/CEXAT11200_1.res
xingapi/api/resfiles/CEXAT11300.res
xingapi/api/resfiles/CEXAT11300_1.res
xingapi/api/resfiles/CFOAQ00600.res
xingapi/api/resfiles/CFOAQ00600_1.res
xingapi/api/resfiles/CFOAQ10100.res
xingapi/api/resfiles/CFOAQ10100_1.res
xingapi/api/resfiles/CFOAT00100.res
xingapi/api/resfiles/CFOAT00100_1.res
xingapi/api/resfiles/CFOAT00200.res
xingapi-1.2.14.dist-info/LICENSE
xingapi-1.2.14.dist-info/METADATA
xingapi-1.2.14.dist-info/WHEEL
xingapi-1.2.14.dist-info/top_level.txt
xingapi-1.2.14.dist-info/RECORD
